{
  "pseudo_logit_rx": {
    "mean": 0.61664,
    "std": 0.07365951217143195
  },
  "pseudo_logit_day": {
    "mean": 0.8257866666666668,
    "std": 0.08381391451702197
  },
  "pseudo_logit_all": {
    "mean": 0.7212133333333333,
    "std": 0.052693506241281766
  },
  "pseudo_lp_rx": {
    "mean": 0.6230133333333334,
    "std": 0.07455721024823823
  },
  "pseudo_lp_day": {
    "mean": 0.8319333333333333,
    "std": 0.08140472276771717
  },
  "pseudo_lp_all": {
    "mean": 0.7274733333333333,
    "std": 0.05141823455199959
  },
  "pseudo_tri_rx": {
    "mean": 0.64128,
    "std": 0.07769928814202726
  },
  "pseudo_tri_day": {
    "mean": 0.8558666666666668,
    "std": 0.06375913006516531
  },
  "pseudo_tri_all": {
    "mean": 0.7485733333333334,
    "std": 0.04363462132043519
  },
  "tau_id": {
    "mean": -1.2858082256317138,
    "std": 0.24970858700413856
  },
  "tau_dom": {
    "mean": 2393.7367316894506,
    "std": 343.1168293718753
  },
  "tau_conf": {
    "mean": 0.9941129279136659,
    "std": 0.014382636228409242
  },
  "variants": {
    "NoAdapt": {
      "stable_acc": {
        "mean": 0.9964500000000001,
        "std": 0.002380826187131974
      },
      "drift_acc_rx": {
        "mean": 0.61664,
        "std": 0.07365951217143195
      },
      "drift_acc_day": {
        "mean": 0.8257866666666668,
        "std": 0.08381391451702197
      },
      "drift_acc_all": {
        "mean": 0.7212133333333333,
        "std": 0.052693506241281766
      },
      "FRR_stable": {
        "mean": 0.09185,
        "std": 0.002261022384281551
      },
      "FAR_unknown_accept": {
        "mean": 0.050586666666666676,
        "std": 0.08031972234470725
      },
      "miss_drift_rx": {
        "mean": 0.17842666666666665,
        "std": 0.05115592894930818
      },
      "miss_drift_day": {
        "mean": 0.43261333333333335,
        "std": 0.11418673517046053
      },
      "miss_drift_all": {
        "mean": 0.30552,
        "std": 0.08014724393958354
      },
      "auc_unknown_eval": {
        "mean": 0.9209615944444444,
        "std": 0.07737872015900171
      }
    },
    "UngatedAdapt": {
      "stable_acc": {
        "mean": 0.9966166666666666,
        "std": 0.0020626304672539952
      },
      "drift_acc_rx": {
        "mean": 0.6161466666666666,
        "std": 0.07400979394647712
      },
      "drift_acc_day": {
        "mean": 0.82584,
        "std": 0.08421639428678163
      },
      "drift_acc_all": {
        "mean": 0.7209933333333334,
        "std": 0.05348271745776076
      },
      "FRR_stable": {
        "mean": 0.12443333333333331,
        "std": 0.05673168818609618
      },
      "FAR_unknown_accept": {
        "mean": 0.04602222222222222,
        "std": 0.07114197246993915
      },
      "miss_drift_rx": {
        "mean": 0.16141333333333335,
        "std": 0.05465685115132208
      },
      "miss_drift_day": {
        "mean": 0.39690666666666674,
        "std": 0.10214667101770865
      },
      "miss_drift_all": {
        "mean": 0.27916,
        "std": 0.07564405653380105
      },
      "auc_unknown_eval": {
        "mean": 0.9335683157407406,
        "std": 0.0665068740179834
      }
    },
    "GatedAdapt": {
      "stable_acc": {
        "mean": 0.9974,
        "std": 0.0016594845250525484
      },
      "drift_acc_rx": {
        "mean": 0.6361733333333334,
        "std": 0.07462898573015118
      },
      "drift_acc_day": {
        "mean": 0.8491066666666666,
        "std": 0.06189652440430992
      },
      "drift_acc_all": {
        "mean": 0.7426400000000001,
        "std": 0.03839113555091709
      },
      "FRR_stable": {
        "mean": 0.0860666666666667,
        "std": 0.004431703961232073
      },
      "FAR_unknown_accept": {
        "mean": 0.04759111111111111,
        "std": 0.07207462333162111
      },
      "miss_drift_rx": {
        "mean": 0.18202666666666667,
        "std": 0.05279031224255703
      },
      "miss_drift_day": {
        "mean": 0.4393066666666667,
        "std": 0.1143903228230236
      },
      "miss_drift_all": {
        "mean": 0.31066666666666665,
        "std": 0.08113275814641362
      },
      "auc_unknown_eval": {
        "mean": 0.9281642990740742,
        "std": 0.06796246698029786
      }
    },
    "GatedSelfSoft": {
      "stable_acc": {
        "mean": 0.9974166666666667,
        "std": 0.0016996731711975967
      },
      "drift_acc_rx": {
        "mean": 0.6325733333333333,
        "std": 0.07721798984404836
      },
      "drift_acc_day": {
        "mean": 0.8559866666666666,
        "std": 0.05174316745018397
      },
      "drift_acc_all": {
        "mean": 0.7442799999999999,
        "std": 0.03878034209923029
      },
      "FRR_stable": {
        "mean": 0.1765,
        "std": 0.0711006719768214
      },
      "FAR_unknown_accept": {
        "mean": 0.010897777777777777,
        "std": 0.02123523556802772
      },
      "miss_drift_rx": {
        "mean": 0.15264,
        "std": 0.05671213234886831
      },
      "miss_drift_day": {
        "mean": 0.3645333333333333,
        "std": 0.1103023722924096
      },
      "miss_drift_all": {
        "mean": 0.25858666666666674,
        "std": 0.08113282826465636
      },
      "auc_unknown_eval": {
        "mean": 0.9771775907407406,
        "std": 0.028269800515848095
      }
    },
    "GatedProtoAgree": {
      "stable_acc": {
        "mean": 0.9975333333333333,
        "std": 0.0013638181696985895
      },
      "drift_acc_rx": {
        "mean": 0.63668,
        "std": 0.07550608393441624
      },
      "drift_acc_day": {
        "mean": 0.8518799999999999,
        "std": 0.06086581817590414
      },
      "drift_acc_all": {
        "mean": 0.7442800000000002,
        "std": 0.040959484588771106
      },
      "FRR_stable": {
        "mean": 0.08578333333333334,
        "std": 0.005185878260558505
      },
      "FAR_unknown_accept": {
        "mean": 0.04590222222222222,
        "std": 0.0705434097682299
      },
      "miss_drift_rx": {
        "mean": 0.18270666666666668,
        "std": 0.05375940806552427
      },
      "miss_drift_day": {
        "mean": 0.4415066666666667,
        "std": 0.1157193586032845
      },
      "miss_drift_all": {
        "mean": 0.3121066666666667,
        "std": 0.08240949082343475
      },
      "auc_unknown_eval": {
        "mean": 0.9302350212962962,
        "std": 0.06833491056968581
      }
    },
    "GatedProtoFusionSoft": {
      "stable_acc": {
        "mean": 0.9975333333333333,
        "std": 0.0015088627063675121
      },
      "drift_acc_rx": {
        "mean": 0.6481066666666667,
        "std": 0.0848201087269077
      },
      "drift_acc_day": {
        "mean": 0.8615466666666666,
        "std": 0.051496008906839884
      },
      "drift_acc_all": {
        "mean": 0.7548266666666668,
        "std": 0.04339878339308603
      },
      "FRR_stable": {
        "mean": 0.19948333333333335,
        "std": 0.07591463407450941
      },
      "FAR_unknown_accept": {
        "mean": 0.007000000000000001,
        "std": 0.012141226573787732
      },
      "miss_drift_rx": {
        "mean": 0.16056,
        "std": 0.06237119848135035
      },
      "miss_drift_day": {
        "mean": 0.3884533333333334,
        "std": 0.11654240544396992
      },
      "miss_drift_all": {
        "mean": 0.2745066666666667,
        "std": 0.08736983308518641
      },
      "auc_unknown_eval": {
        "mean": 0.956017424074074,
        "std": 0.058850500756907766
      }
    },
    "GatedTriAgree": {
      "stable_acc": {
        "mean": 0.9975666666666667,
        "std": 0.0013368703086770314
      },
      "drift_acc_rx": {
        "mean": 0.6366400000000001,
        "std": 0.07630907445674101
      },
      "drift_acc_day": {
        "mean": 0.8524666666666668,
        "std": 0.06160894595935093
      },
      "drift_acc_all": {
        "mean": 0.7445533333333333,
        "std": 0.04180031153525586
      },
      "FRR_stable": {
        "mean": 0.08558333333333336,
        "std": 0.005206833117271097
      },
      "FAR_unknown_accept": {
        "mean": 0.04933333333333333,
        "std": 0.07492248504575978
      },
      "miss_drift_rx": {
        "mean": 0.18319999999999997,
        "std": 0.05372663316374023
      },
      "miss_drift_day": {
        "mean": 0.44144,
        "std": 0.11532700252374165
      },
      "miss_drift_all": {
        "mean": 0.31232,
        "std": 0.08221750178642015
      },
      "auc_unknown_eval": {
        "mean": 0.926114636111111,
        "std": 0.07070365847966377
      }
    },
    "GatedTriFusionSoft": {
      "stable_acc": {
        "mean": 0.9976,
        "std": 0.0014204850501775075
      },
      "drift_acc_rx": {
        "mean": 0.6424133333333334,
        "std": 0.08015325764503343
      },
      "drift_acc_day": {
        "mean": 0.8576933333333332,
        "std": 0.05261161004104618
      },
      "drift_acc_all": {
        "mean": 0.7500533333333333,
        "std": 0.0385631003825044
      },
      "FRR_stable": {
        "mean": 0.1569333333333333,
        "std": 0.07735855192256093
      },
      "FAR_unknown_accept": {
        "mean": 0.007573333333333333,
        "std": 0.012225723942815243
      },
      "miss_drift_rx": {
        "mean": 0.16542666666666667,
        "std": 0.06306606905988883
      },
      "miss_drift_day": {
        "mean": 0.4019466666666666,
        "std": 0.1175385962141798
      },
      "miss_drift_all": {
        "mean": 0.28368666666666664,
        "std": 0.08823243696812037
      },
      "auc_unknown_eval": {
        "mean": 0.9718693824074073,
        "std": 0.034287233387839525
      }
    },
    "ConfThreshSoft": {
      "stable_acc": {
        "mean": 0.9975166666666668,
        "std": 0.0014116578118573183
      },
      "drift_acc_rx": {
        "mean": 0.6333999999999999,
        "std": 0.0730288223161848
      },
      "drift_acc_day": {
        "mean": 0.8563466666666666,
        "std": 0.05692220656299262
      },
      "drift_acc_all": {
        "mean": 0.7448733333333333,
        "std": 0.037190359563258384
      },
      "FRR_stable": {
        "mean": 0.16128333333333333,
        "std": 0.08133990069113954
      },
      "FAR_unknown_accept": {
        "mean": 0.03144,
        "std": 0.06459643746626692
      },
      "miss_drift_rx": {
        "mean": 0.14856,
        "std": 0.056421408072547155
      },
      "miss_drift_day": {
        "mean": 0.3728533333333333,
        "std": 0.11587955739569522
      },
      "miss_drift_all": {
        "mean": 0.26070666666666664,
        "std": 0.08452765858975786
      },
      "auc_unknown_eval": {
        "mean": 0.929379512962963,
        "std": 0.0757935896588284
      }
    },
    "AgreementConfSoft": {
      "stable_acc": {
        "mean": 0.9975833333333334,
        "std": 0.0013540064007726584
      },
      "drift_acc_rx": {
        "mean": 0.6383866666666667,
        "std": 0.07588738322892241
      },
      "drift_acc_day": {
        "mean": 0.8564399999999999,
        "std": 0.05890879730566563
      },
      "drift_acc_all": {
        "mean": 0.7474133333333333,
        "std": 0.04140308952508523
      },
      "FRR_stable": {
        "mean": 0.1149,
        "std": 0.05949793180345757
      },
      "FAR_unknown_accept": {
        "mean": 0.03012888888888889,
        "std": 0.05913320121911
      },
      "miss_drift_rx": {
        "mean": 0.17786666666666665,
        "std": 0.056544024146382314
      },
      "miss_drift_day": {
        "mean": 0.4308933333333333,
        "std": 0.11859322521403433
      },
      "miss_drift_all": {
        "mean": 0.30438000000000004,
        "std": 0.08529872371065507
      },
      "auc_unknown_eval": {
        "mean": 0.9486643907407408,
        "std": 0.05717521021038123
      }
    },
    "ProtoRefineSoft": {
      "stable_acc": {
        "mean": 0.9974833333333334,
        "std": 0.0014408716497700644
      },
      "drift_acc_rx": {
        "mean": 0.65444,
        "std": 0.09046156802139176
      },
      "drift_acc_day": {
        "mean": 0.8659866666666667,
        "std": 0.045999563282951086
      },
      "drift_acc_all": {
        "mean": 0.7602133333333333,
        "std": 0.044135335302025534
      },
      "FRR_stable": {
        "mean": 0.29118333333333335,
        "std": 0.06783237919066873
      },
      "FAR_unknown_accept": {
        "mean": 0.006373333333333334,
        "std": 0.012114714244858105
      },
      "miss_drift_rx": {
        "mean": 0.15186666666666668,
        "std": 0.06455729582661006
      },
      "miss_drift_day": {
        "mean": 0.36084000000000005,
        "std": 0.12354522770584417
      },
      "miss_drift_all": {
        "mean": 0.2563533333333334,
        "std": 0.09226447877945469
      },
      "auc_unknown_eval": {
        "mean": 0.9217994212962963,
        "std": 0.07356297199326135
      }
    },
    "ReliableEntropySplit": {
      "stable_acc": {
        "mean": 0.9962666666666667,
        "std": 0.002177791950067262
      },
      "drift_acc_rx": {
        "mean": 0.6423066666666668,
        "std": 0.0893363143781221
      },
      "drift_acc_day": {
        "mean": 0.8582666666666665,
        "std": 0.0622121102894498
      },
      "drift_acc_all": {
        "mean": 0.7502866666666667,
        "std": 0.055829552508804274
      },
      "FRR_stable": {
        "mean": 0.4810999999999999,
        "std": 0.13316436585413283
      },
      "FAR_unknown_accept": {
        "mean": 0.006586666666666668,
        "std": 0.012807926558036215
      },
      "miss_drift_rx": {
        "mean": 0.11933333333333332,
        "std": 0.05853120725068143
      },
      "miss_drift_day": {
        "mean": 0.23465333333333332,
        "std": 0.09029671976323392
      },
      "miss_drift_all": {
        "mean": 0.1769933333333333,
        "std": 0.07206021371047966
      },
      "auc_unknown_eval": {
        "mean": 0.8121950231481482,
        "std": 0.11298689348824724
      }
    },
    "TwoStageUnknown": {
      "stable_acc": {
        "mean": 0.9960333333333334,
        "std": 0.001933333333333337
      },
      "drift_acc_rx": {
        "mean": 0.6386533333333333,
        "std": 0.09442530169398454
      },
      "drift_acc_day": {
        "mean": 0.8488000000000001,
        "std": 0.04986916214789792
      },
      "drift_acc_all": {
        "mean": 0.7437266666666666,
        "std": 0.05070373380947622
      },
      "FRR_stable": {
        "mean": 0.6612833333333333,
        "std": 0.14605216533827906
      },
      "FAR_unknown_accept": {
        "mean": 0.003088888888888889,
        "std": 0.006799709507230147
      },
      "miss_drift_rx": {
        "mean": 0.06274666666666667,
        "std": 0.04628426946598596
      },
      "miss_drift_day": {
        "mean": 0.11558666666666666,
        "std": 0.08412859363300129
      },
      "miss_drift_all": {
        "mean": 0.08916666666666666,
        "std": 0.0631369763116494
      },
      "auc_unknown_eval": {
        "mean": 0.7982593731481481,
        "std": 0.11747967819626469
      }
    },
    "GCODWFA_Lite": {
      "stable_acc": {
        "mean": 0.9968666666666667,
        "std": 0.0014535397406943427
      },
      "drift_acc_rx": {
        "mean": 0.6498400000000001,
        "std": 0.08315261043540498
      },
      "drift_acc_day": {
        "mean": 0.8607333333333334,
        "std": 0.07051228419376458
      },
      "drift_acc_all": {
        "mean": 0.7552866666666666,
        "std": 0.05257212019903916
      },
      "FRR_stable": {
        "mean": 0.6865833333333333,
        "std": 0.14428179410830427
      },
      "FAR_unknown_accept": {
        "mean": 0.01801777777777778,
        "std": 0.049410766857856815
      },
      "miss_drift_rx": {
        "mean": 0.03277333333333333,
        "std": 0.0254489851358447
      },
      "miss_drift_day": {
        "mean": 0.11631999999999999,
        "std": 0.08423525152808652
      },
      "miss_drift_all": {
        "mean": 0.07454666666666665,
        "std": 0.051307927046196064
      },
      "auc_unknown_eval": {
        "mean": 0.8301630712962962,
        "std": 0.0788641197553189
      }
    },
    "RAINCOAT_Lite": {
      "stable_acc": {
        "mean": 0.9963833333333335,
        "std": 0.0019174636024359602
      },
      "drift_acc_rx": {
        "mean": 0.6623866666666666,
        "std": 0.09671845417384305
      },
      "drift_acc_day": {
        "mean": 0.8788133333333334,
        "std": 0.05398436646124712
      },
      "drift_acc_all": {
        "mean": 0.7706000000000001,
        "std": 0.05658578541569527
      },
      "FRR_stable": {
        "mean": 0.831,
        "std": 0.11358972224633705
      },
      "FAR_unknown_accept": {
        "mean": 0.0026666666666666666,
        "std": 0.006972467901824669
      },
      "miss_drift_rx": {
        "mean": 0.024226666666666664,
        "std": 0.027065799657706606
      },
      "miss_drift_day": {
        "mean": 0.034973333333333335,
        "std": 0.044456512583772374
      },
      "miss_drift_all": {
        "mean": 0.0296,
        "std": 0.034098875836797514
      },
      "auc_unknown_eval": {
        "mean": 0.7665972611111113,
        "std": 0.13367816473708188
      }
    },
    "DG_RAINCOAT": {
      "stable_acc": {
        "mean": 0.9963333333333334,
        "std": 0.0017989194287435714
      },
      "drift_acc_rx": {
        "mean": 0.6399866666666667,
        "std": 0.09317078607470143
      },
      "drift_acc_day": {
        "mean": 0.8600133333333333,
        "std": 0.05058304327209531
      },
      "drift_acc_all": {
        "mean": 0.75,
        "std": 0.05511299503948431
      },
      "FRR_stable": {
        "mean": 0.40513333333333335,
        "std": 0.06548554972069962
      },
      "FAR_unknown_accept": {
        "mean": 0.0047599999999999995,
        "std": 0.009119545147851602
      },
      "miss_drift_rx": {
        "mean": 0.11096,
        "std": 0.05729784327917103
      },
      "miss_drift_day": {
        "mean": 0.26348,
        "std": 0.11132758787570232
      },
      "miss_drift_all": {
        "mean": 0.18721999999999997,
        "std": 0.08154570252318635
      },
      "auc_unknown_eval": {
        "mean": 0.8969594722222222,
        "std": 0.05800113612776919
      }
    },
    "ThreeBucketV5Soft": {
      "stable_acc": {
        "mean": 0.9962333333333333,
        "std": 0.0017891649200426165
      },
      "drift_acc_rx": {
        "mean": 0.6298400000000001,
        "std": 0.09063975679088682
      },
      "drift_acc_day": {
        "mean": 0.8411066666666668,
        "std": 0.061880438122416545
      },
      "drift_acc_all": {
        "mean": 0.7354733333333333,
        "std": 0.05090600663095771
      },
      "FRR_stable": {
        "mean": 0.5715666666666666,
        "std": 0.11730878531086711
      },
      "FAR_unknown_accept": {
        "mean": 0.0040888888888888884,
        "std": 0.008201896799589173
      },
      "miss_drift_rx": {
        "mean": 0.07130666666666667,
        "std": 0.05743579371785507
      },
      "miss_drift_day": {
        "mean": 0.1684,
        "std": 0.10834073820846687
      },
      "miss_drift_all": {
        "mean": 0.11985333333333333,
        "std": 0.08100819327560503
      },
      "auc_unknown_eval": {
        "mean": 0.8613953888888889,
        "std": 0.09314092742714773
      }
    },
    "ThreeBucketV5EMA": {
      "stable_acc": {
        "mean": 0.9961166666666668,
        "std": 0.001734935157289752
      },
      "drift_acc_rx": {
        "mean": 0.6290133333333333,
        "std": 0.09261919551463281
      },
      "drift_acc_day": {
        "mean": 0.84316,
        "std": 0.06756068021498238
      },
      "drift_acc_all": {
        "mean": 0.7360866666666667,
        "std": 0.05965076361623546
      },
      "FRR_stable": {
        "mean": 0.5309166666666667,
        "std": 0.12748910628842852
      },
      "FAR_unknown_accept": {
        "mean": 0.003671111111111111,
        "std": 0.0065974540544061384
      },
      "miss_drift_rx": {
        "mean": 0.07442666666666665,
        "std": 0.05179519668849612
      },
      "miss_drift_day": {
        "mean": 0.16945333333333334,
        "std": 0.10750863035124203
      },
      "miss_drift_all": {
        "mean": 0.12194,
        "std": 0.07646384592298071
      },
      "auc_unknown_eval": {
        "mean": 0.8847383351851851,
        "std": 0.08397891526877187
      }
    },
    "ThreeBucketV5EMAProto": {
      "stable_acc": {
        "mean": 0.9962333333333333,
        "std": 0.001980740602232758
      },
      "drift_acc_rx": {
        "mean": 0.6322266666666666,
        "std": 0.0939675461706505
      },
      "drift_acc_day": {
        "mean": 0.84224,
        "std": 0.06305303023822267
      },
      "drift_acc_all": {
        "mean": 0.7372333333333333,
        "std": 0.05602094846275513
      },
      "FRR_stable": {
        "mean": 0.49881666666666663,
        "std": 0.11875550747462434
      },
      "FAR_unknown_accept": {
        "mean": 0.00364,
        "std": 0.007267535116300895
      },
      "miss_drift_rx": {
        "mean": 0.07797333333333334,
        "std": 0.050697001445406564
      },
      "miss_drift_day": {
        "mean": 0.18917333333333336,
        "std": 0.11083682179973706
      },
      "miss_drift_all": {
        "mean": 0.13357333333333332,
        "std": 0.0783064504225404
      },
      "auc_unknown_eval": {
        "mean": 0.9005437055555555,
        "std": 0.07512226584998898
      }
    },
    "ThreeBucketV6Curriculum": {
      "stable_acc": {
        "mean": 0.9971,
        "std": 0.00176965156645784
      },
      "drift_acc_rx": {
        "mean": 0.6441866666666668,
        "std": 0.08964394160603753
      },
      "drift_acc_day": {
        "mean": 0.8494133333333334,
        "std": 0.05735211165346147
      },
      "drift_acc_all": {
        "mean": 0.7467999999999999,
        "std": 0.04330298937589516
      },
      "FRR_stable": {
        "mean": 0.26958333333333334,
        "std": 0.1380717406117398
      },
      "FAR_unknown_accept": {
        "mean": 0.005048888888888889,
        "std": 0.009681856775292845
      },
      "miss_drift_rx": {
        "mean": 0.12824,
        "std": 0.06183170851414166
      },
      "miss_drift_day": {
        "mean": 0.32775999999999994,
        "std": 0.15201007335041977
      },
      "miss_drift_all": {
        "mean": 0.228,
        "std": 0.10492510556476833
      },
      "auc_unknown_eval": {
        "mean": 0.9535447314814816,
        "std": 0.04390577738308085
      }
    },
    "ThreeBucketV7Promotion": {
      "stable_acc": {
        "mean": 0.9673166666666667,
        "std": 0.14643305637730847
      },
      "drift_acc_rx": {
        "mean": 0.6295066666666667,
        "std": 0.11182848454466132
      },
      "drift_acc_day": {
        "mean": 0.8203733333333334,
        "std": 0.1314613021217862
      },
      "drift_acc_all": {
        "mean": 0.72494,
        "std": 0.105515526819516
      },
      "FRR_stable": {
        "mean": 0.24618333333333337,
        "std": 0.1998410715766128
      },
      "FAR_unknown_accept": {
        "mean": 0.006511111111111111,
        "std": 0.011755870611195093
      },
      "miss_drift_rx": {
        "mean": 0.13982666666666668,
        "std": 0.07410317851932309
      },
      "miss_drift_day": {
        "mean": 0.34942666666666666,
        "std": 0.1735873144366642
      },
      "miss_drift_all": {
        "mean": 0.24462666666666671,
        "std": 0.12202832348816946
      },
      "auc_unknown_eval": {
        "mean": 0.9418255814814814,
        "std": 0.09466251545491979
      }
    },
    "ThreeBucketV8Adaptive": {
      "stable_acc": {
        "mean": 0.9964833333333334,
        "std": 0.001775919167329668
      },
      "drift_acc_rx": {
        "mean": 0.6434266666666667,
        "std": 0.09458040764931769
      },
      "drift_acc_day": {
        "mean": 0.8518533333333334,
        "std": 0.06012402588723487
      },
      "drift_acc_all": {
        "mean": 0.7476400000000001,
        "std": 0.05703959014968853
      },
      "FRR_stable": {
        "mean": 0.36765000000000003,
        "std": 0.10130104200407372
      },
      "FAR_unknown_accept": {
        "mean": 0.00499111111111111,
        "std": 0.009389772213542895
      },
      "miss_drift_rx": {
        "mean": 0.11570666666666667,
        "std": 0.061279274727358765
      },
      "miss_drift_day": {
        "mean": 0.2782266666666667,
        "std": 0.12156584754316851
      },
      "miss_drift_all": {
        "mean": 0.19696666666666665,
        "std": 0.08914678282971791
      },
      "auc_unknown_eval": {
        "mean": 0.9252043574074075,
        "std": 0.05174277469099105
      }
    },
    "OracleGatePseudoAdapt": {
      "stable_acc": {
        "mean": 0.9965833333333333,
        "std": 0.00217944947177034
      },
      "drift_acc_rx": {
        "mean": 0.6164533333333333,
        "std": 0.07439389939145996
      },
      "drift_acc_day": {
        "mean": 0.8260666666666668,
        "std": 0.08425105340587737
      },
      "drift_acc_all": {
        "mean": 0.72126,
        "std": 0.05308887893586252
      },
      "FRR_stable": {
        "mean": 0.12486666666666664,
        "std": 0.0687848618681627
      },
      "FAR_unknown_accept": {
        "mean": 0.03745333333333334,
        "std": 0.05853982010795391
      },
      "miss_drift_rx": {
        "mean": 0.16757333333333332,
        "std": 0.05988288718638888
      },
      "miss_drift_day": {
        "mean": 0.41053333333333336,
        "std": 0.11566092204754762
      },
      "miss_drift_all": {
        "mean": 0.28905333333333333,
        "std": 0.08582449430216424
      },
      "auc_unknown_eval": {
        "mean": 0.9281227240740739,
        "std": 0.06995243704490149
      }
    },
    "OracleLabelAdapt": {
      "stable_acc": {
        "mean": 0.9967666666666668,
        "std": 0.0019800392813162935
      },
      "drift_acc_rx": {
        "mean": 0.86444,
        "std": 0.0665599626068271
      },
      "drift_acc_day": {
        "mean": 0.9831466666666668,
        "std": 0.01563502620542876
      },
      "drift_acc_all": {
        "mean": 0.9237933333333334,
        "std": 0.03882502858266102
      },
      "FRR_stable": {
        "mean": 0.53405,
        "std": 0.1969673027010659
      },
      "FAR_unknown_accept": {
        "mean": 0.007600000000000001,
        "std": 0.016178418790719358
      },
      "miss_drift_rx": {
        "mean": 0.0626,
        "std": 0.049568000430385194
      },
      "miss_drift_day": {
        "mean": 0.16826666666666668,
        "std": 0.10094759916797318
      },
      "miss_drift_all": {
        "mean": 0.11543333333333333,
        "std": 0.07265648246677267
      },
      "auc_unknown_eval": {
        "mean": 0.8418547194444443,
        "std": 0.11099154424053559
      }
    }
  },
  "selection": {
    "UngatedAdapt": {
      "sel_precision": {
        "mean": 0.4000000000000001,
        "std": 5.551115123125783e-17
      },
      "sel_recall": {
        "mean": 1.0,
        "std": 0.0
      },
      "sel_keep": {
        "mean": 1.0,
        "std": 0.0
      },
      "pseudo_acc_selected": {
        "mean": 0.72309,
        "std": 0.05321789548638692
      },
      "unknown_cand_keep": {
        "mean": 0.0,
        "std": 0.0
      },
      "unknown_cand_precision": {
        "mean": NaN,
        "std": NaN
      }
    },
    "GatedAdapt": {
      "sel_precision": {
        "mean": 0.5195461098328047,
        "std": 0.2026155100496466
      },
      "sel_recall": {
        "mean": 0.17368999999999996,
        "std": 0.03687690876415754
      },
      "sel_keep": {
        "mean": 0.16334800000000002,
        "std": 0.09131947489993578
      },
      "pseudo_acc_selected": {
        "mean": 0.9208405716291596,
        "std": 0.06960542427604835
      },
      "unknown_cand_keep": {
        "mean": 0.0,
        "std": 0.0
      },
      "unknown_cand_precision": {
        "mean": NaN,
        "std": NaN
      }
    },
    "GatedSelfSoft": {
      "sel_precision": {
        "mean": 0.5195461098328047,
        "std": 0.2026155100496466
      },
      "sel_recall": {
        "mean": 0.17368999999999996,
        "std": 0.03687690876415754
      },
      "sel_keep": {
        "mean": 0.16334800000000002,
        "std": 0.09131947489993578
      },
      "pseudo_acc_selected": {
        "mean": 0.9208405716291596,
        "std": 0.06960542427604835
      },
      "unknown_cand_keep": {
        "mean": 0.0,
        "std": 0.0
      },
      "unknown_cand_precision": {
        "mean": NaN,
        "std": NaN
      }
    },
    "GatedProtoAgree": {
      "sel_precision": {
        "mean": 0.5192499724161747,
        "std": 0.20273450881910107
      },
      "sel_recall": {
        "mean": 0.17344999999999997,
        "std": 0.03670776484614665
      },
      "sel_keep": {
        "mean": 0.16325200000000004,
        "std": 0.09129960402980948
      },
      "pseudo_acc_selected": {
        "mean": 0.9220227410759599,
        "std": 0.07063797162161567
      },
      "unknown_cand_keep": {
        "mean": 0.0,
        "std": 0.0
      },
      "unknown_cand_precision": {
        "mean": NaN,
        "std": NaN
      }
    },
    "GatedProtoFusionSoft": {
      "sel_precision": {
        "mean": 0.5195461098328047,
        "std": 0.2026155100496466
      },
      "sel_recall": {
        "mean": 0.17368999999999996,
        "std": 0.03687690876415754
      },
      "sel_keep": {
        "mean": 0.16334800000000002,
        "std": 0.09131947489993578
      },
      "pseudo_acc_selected": {
        "mean": 0.9220257568143446,
        "std": 0.0706411935335542
      },
      "unknown_cand_keep": {
        "mean": 0.0,
        "std": 0.0
      },
      "unknown_cand_precision": {
        "mean": NaN,
        "std": NaN
      }
    },
    "GatedTriAgree": {
      "sel_precision": {
        "mean": 0.5192499724161747,
        "std": 0.20273450881910107
      },
      "sel_recall": {
        "mean": 0.17344999999999997,
        "std": 0.03670776484614665
      },
      "sel_keep": {
        "mean": 0.16325200000000004,
        "std": 0.09129960402980948
      },
      "pseudo_acc_selected": {
        "mean": 0.9220227410759599,
        "std": 0.07063797162161567
      },
      "unknown_cand_keep": {
        "mean": 0.0,
        "std": 0.0
      },
      "unknown_cand_precision": {
        "mean": NaN,
        "std": NaN
      }
    },
    "GatedTriFusionSoft": {
      "sel_precision": {
        "mean": 0.5195461098328047,
        "std": 0.2026155100496466
      },
      "sel_recall": {
        "mean": 0.17368999999999996,
        "std": 0.03687690876415754
      },
      "sel_keep": {
        "mean": 0.16334800000000002,
        "std": 0.09131947489993578
      },
      "pseudo_acc_selected": {
        "mean": 0.9220257568143446,
        "std": 0.0706411935335542
      },
      "unknown_cand_keep": {
        "mean": 0.0,
        "std": 0.0
      },
      "unknown_cand_precision": {
        "mean": NaN,
        "std": NaN
      }
    },
    "ConfThreshSoft": {
      "sel_precision": {
        "mean": 0.6683161265099549,
        "std": 0.2786999438799666
      },
      "sel_recall": {
        "mean": 0.06078,
        "std": 0.0657755015184225
      },
      "sel_keep": {
        "mean": 0.04843599999999999,
        "std": 0.06419226669934626
      },
      "pseudo_acc_selected": {
        "mean": 0.98208589671233,
        "std": 0.03307587670435484
      },
      "unknown_cand_keep": {
        "mean": 0.0,
        "std": 0.0
      },
      "unknown_cand_precision": {
        "mean": NaN,
        "std": NaN
      }
    },
    "AgreementConfSoft": {
      "sel_precision": {
        "mean": 0.6683161265099549,
        "std": 0.2786999438799666
      },
      "sel_recall": {
        "mean": 0.06078,
        "std": 0.0657755015184225
      },
      "sel_keep": {
        "mean": 0.04843599999999999,
        "std": 0.06419226669934626
      },
      "pseudo_acc_selected": {
        "mean": 0.98208589671233,
        "std": 0.03307587670435484
      },
      "unknown_cand_keep": {
        "mean": 0.0,
        "std": 0.0
      },
      "unknown_cand_precision": {
        "mean": NaN,
        "std": NaN
      }
    },
    "ProtoRefineSoft": {
      "sel_precision": {
        "mean": 0.5195461098328047,
        "std": 0.2026155100496466
      },
      "sel_recall": {
        "mean": 0.17368999999999996,
        "std": 0.03687690876415754
      },
      "sel_keep": {
        "mean": 0.16334800000000002,
        "std": 0.09131947489993578
      },
      "pseudo_acc_selected": {
        "mean": 0.9220257568143446,
        "std": 0.0706411935335542
      },
      "unknown_cand_keep": {
        "mean": 0.0,
        "std": 0.0
      },
      "unknown_cand_precision": {
        "mean": NaN,
        "std": NaN
      }
    },
    "ReliableEntropySplit": {
      "sel_precision": {
        "mean": 0.6683161265099549,
        "std": 0.2786999438799666
      },
      "sel_recall": {
        "mean": 0.06078,
        "std": 0.0657755015184225
      },
      "sel_keep": {
        "mean": 0.04843599999999999,
        "std": 0.06419226669934626
      },
      "pseudo_acc_selected": {
        "mean": 0.98208589671233,
        "std": 0.03307587670435484
      },
      "unknown_cand_keep": {
        "mean": 0.11491199999999999,
        "std": 0.07011037195736448
      },
      "unknown_cand_precision": {
        "mean": 0.5259863481503996,
        "std": 0.24292021154077728
      }
    },
    "TwoStageUnknown": {
      "sel_precision": {
        "mean": 0.6508352144047048,
        "std": 0.29165924563208867
      },
      "sel_recall": {
        "mean": 0.061770000000000005,
        "std": 0.06680082035424414
      },
      "sel_keep": {
        "mean": 0.051747999999999995,
        "std": 0.06982466681624767
      },
      "pseudo_acc_selected": {
        "mean": 0.9885720947653812,
        "std": 0.034986323263331634
      },
      "unknown_cand_keep": {
        "mean": 0.1116,
        "std": 0.07080594890261693
      },
      "unknown_cand_precision": {
        "mean": 0.5228240255177323,
        "std": 0.2372047428527419
      }
    },
    "GCODWFA_Lite": {
      "sel_precision": {
        "mean": 0.6508352144047048,
        "std": 0.29165924563208867
      },
      "sel_recall": {
        "mean": 0.061770000000000005,
        "std": 0.06680082035424414
      },
      "sel_keep": {
        "mean": 0.051747999999999995,
        "std": 0.06982466681624767
      },
      "pseudo_acc_selected": {
        "mean": 0.9885720947653812,
        "std": 0.034986323263331634
      },
      "unknown_cand_keep": {
        "mean": 0.1116,
        "std": 0.07080594890261693
      },
      "unknown_cand_precision": {
        "mean": 0.5228240255177323,
        "std": 0.2372047428527419
      }
    },
    "RAINCOAT_Lite": {
      "sel_precision": {
        "mean": 0.6508352144047048,
        "std": 0.29165924563208867
      },
      "sel_recall": {
        "mean": 0.061770000000000005,
        "std": 0.06680082035424414
      },
      "sel_keep": {
        "mean": 0.051747999999999995,
        "std": 0.06982466681624767
      },
      "pseudo_acc_selected": {
        "mean": 0.9885720947653812,
        "std": 0.034986323263331634
      },
      "unknown_cand_keep": {
        "mean": 0.1116,
        "std": 0.07080594890261693
      },
      "unknown_cand_precision": {
        "mean": 0.5228240255177323,
        "std": 0.2372047428527419
      }
    },
    "DG_RAINCOAT": {
      "sel_precision": {
        "mean": 0.5696417500985567,
        "std": 0.16598441888051296
      },
      "sel_recall": {
        "mean": 0.07913,
        "std": 0.02926244350699374
      },
      "sel_keep": {
        "mean": 0.061964,
        "std": 0.03333411321754338
      },
      "pseudo_acc_selected": {
        "mean": 0.9563328025926091,
        "std": 0.0430400497777302
      },
      "unknown_cand_keep": {
        "mean": 0.013063999999999997,
        "std": 0.00730976771176759
      },
      "unknown_cand_precision": {
        "mean": 0.0,
        "std": 0.0
      }
    },
    "ThreeBucketV5Soft": {
      "sel_precision": {
        "mean": 0.6523191818215301,
        "std": 0.20446523676109468
      },
      "sel_recall": {
        "mean": 0.09747,
        "std": 0.033930688174571406
      },
      "sel_keep": {
        "mean": 0.068604,
        "std": 0.03833723495506686
      },
      "pseudo_acc_selected": {
        "mean": 0.9734095754811939,
        "std": 0.03406410402177256
      },
      "unknown_cand_keep": {
        "mean": 0.013063999999999997,
        "std": 0.00730976771176759
      },
      "unknown_cand_precision": {
        "mean": 0.5468165330046498,
        "std": 0.2719086398159185
      }
    },
    "ThreeBucketV5EMA": {
      "sel_precision": {
        "mean": 0.6523191818215301,
        "std": 0.20446523676109468
      },
      "sel_recall": {
        "mean": 0.09747,
        "std": 0.033930688174571406
      },
      "sel_keep": {
        "mean": 0.068604,
        "std": 0.03833723495506686
      },
      "pseudo_acc_selected": {
        "mean": 0.9734095754811939,
        "std": 0.03406410402177256
      },
      "unknown_cand_keep": {
        "mean": 0.013063999999999997,
        "std": 0.00730976771176759
      },
      "unknown_cand_precision": {
        "mean": 0.5468165330046498,
        "std": 0.2719086398159185
      }
    },
    "ThreeBucketV5EMAProto": {
      "sel_precision": {
        "mean": 0.6523191818215301,
        "std": 0.20446523676109468
      },
      "sel_recall": {
        "mean": 0.09747,
        "std": 0.033930688174571406
      },
      "sel_keep": {
        "mean": 0.068604,
        "std": 0.03833723495506686
      },
      "pseudo_acc_selected": {
        "mean": 0.9734095754811939,
        "std": 0.03406410402177256
      },
      "unknown_cand_keep": {
        "mean": 0.013063999999999997,
        "std": 0.00730976771176759
      },
      "unknown_cand_precision": {
        "mean": 0.5468165330046498,
        "std": 0.2719086398159185
      }
    },
    "ThreeBucketV6Curriculum": {
      "sel_precision": {
        "mean": 0.5280486501784356,
        "std": 0.20161282208988085
      },
      "sel_recall": {
        "mean": 0.16301000000000002,
        "std": 0.034086102739973076
      },
      "sel_keep": {
        "mean": 0.150284,
        "std": 0.08400977885936851
      },
      "pseudo_acc_selected": {
        "mean": 0.932962481631404,
        "std": 0.06233441852452263
      },
      "unknown_cand_keep": {
        "mean": 0.013063999999999997,
        "std": 0.00730976771176759
      },
      "unknown_cand_precision": {
        "mean": 0.5782783095323986,
        "std": 0.28378120642021204
      }
    },
    "ThreeBucketV7Promotion": {
      "sel_precision": {
        "mean": 0.6062469664646161,
        "std": 0.13466851613776026
      },
      "sel_recall": {
        "mean": 0.09908,
        "std": 0.03911558001615213
      },
      "sel_keep": {
        "mean": 0.071856,
        "std": 0.040175177211805795
      },
      "pseudo_acc_selected": {
        "mean": 0.9805099423459638,
        "std": 0.023922829175763532
      },
      "unknown_cand_keep": {
        "mean": 0.009796,
        "std": 0.005486600404622155
      },
      "unknown_cand_precision": {
        "mean": 0.5487655014838332,
        "std": 0.2766203574771559
      }
    },
    "ThreeBucketV8Adaptive": {
      "sel_precision": {
        "mean": 0.546956353525598,
        "std": 0.1983343834477555
      },
      "sel_recall": {
        "mean": 0.1323,
        "std": 0.032151049749580496
      },
      "sel_keep": {
        "mean": 0.115984,
        "std": 0.06483515515520881
      },
      "pseudo_acc_selected": {
        "mean": 0.9484834354511179,
        "std": 0.05283484251095104
      },
      "unknown_cand_keep": {
        "mean": 0.013063999999999997,
        "std": 0.00730976771176759
      },
      "unknown_cand_precision": {
        "mean": 0.5426166697292778,
        "std": 0.25622316105024107
      }
    },
    "OracleGatePseudoAdapt": {
      "sel_precision": {
        "mean": 1.0,
        "std": 0.0
      },
      "sel_recall": {
        "mean": 1.0,
        "std": 0.0
      },
      "sel_keep": {
        "mean": 0.4000000000000001,
        "std": 5.551115123125783e-17
      },
      "pseudo_acc_selected": {
        "mean": 0.72309,
        "std": 0.05321789548638692
      },
      "unknown_cand_keep": {
        "mean": 0.0,
        "std": 0.0
      },
      "unknown_cand_precision": {
        "mean": NaN,
        "std": NaN
      }
    },
    "OracleLabelAdapt": {
      "sel_precision": {
        "mean": 1.0,
        "std": 0.0
      },
      "sel_recall": {
        "mean": 1.0,
        "std": 0.0
      },
      "sel_keep": {
        "mean": 0.4000000000000001,
        "std": 5.551115123125783e-17
      },
      "pseudo_acc_selected": {
        "mean": 1.0,
        "std": 0.0
      },
      "unknown_cand_keep": {
        "mean": 0.0,
        "std": 0.0
      },
      "unknown_cand_precision": {
        "mean": NaN,
        "std": NaN
      }
    }
  },
  "bucket_stats": {
    "DG_RAINCOAT": {
      "reliable_size": {
        "mean": 177.2,
        "std": 122.62038982159534
      },
      "ambiguous_size": {
        "mean": 801.64,
        "std": 431.88154672317273
      },
      "unknown_size": {
        "mean": 98.44,
        "std": 54.73213315777122
      },
      "reliable_keep": {
        "mean": 0.01772,
        "std": 0.012262038982159534
      },
      "ambiguous_keep": {
        "mean": 0.08016400000000001,
        "std": 0.04318815467231727
      },
      "unknown_keep": {
        "mean": 0.009844,
        "std": 0.0054732133157771225
      },
      "stage2_reliable_size": {
        "mean": 177.2,
        "std": 122.62038982159534
      },
      "stage2_ambiguous_size": {
        "mean": 801.64,
        "std": 431.88154672317273
      },
      "stage2_unknown_size": {
        "mean": 98.44,
        "std": 54.73213315777122
      },
      "common_score_gate_mean": {
        "mean": 0.5787862038612366,
        "std": 0.05082094125705205
      },
      "unknown_score_gate_mean": {
        "mean": 0.38628090023994444,
        "std": 0.053884514714842895
      },
      "move_gate_mean": {
        "mean": 0.18109490722417831,
        "std": 0.1355758867180185
      },
      "stable_pred_ratio": {
        "mean": 0.9850940370559692,
        "std": 0.07148143765330701
      }
    },
    "ThreeBucketV5Soft": {
      "reliable_size": {
        "mean": 196.04,
        "std": 109.49355414817805
      },
      "ambiguous_size": {
        "mean": 490.0,
        "std": 273.87909741343896
      },
      "unknown_size": {
        "mean": 130.64,
        "std": 73.09767711767591
      },
      "reliable_keep": {
        "mean": 0.019604,
        "std": 0.010949355414817804
      },
      "ambiguous_keep": {
        "mean": 0.048999999999999995,
        "std": 0.027387909741343898
      },
      "unknown_keep": {
        "mean": 0.013063999999999997,
        "std": 0.00730976771176759
      },
      "bucket_score_gate_mean": {
        "mean": 0.5815556037425995,
        "std": 0.06241620881157872
      },
      "unknown_score_gate_mean": {
        "mean": 0.40952964425086974,
        "std": 0.08526177378060049
      }
    },
    "ThreeBucketV5EMA": {
      "reliable_size": {
        "mean": 196.04,
        "std": 109.49355414817805
      },
      "ambiguous_size": {
        "mean": 490.0,
        "std": 273.87909741343896
      },
      "unknown_size": {
        "mean": 130.64,
        "std": 73.09767711767591
      },
      "reliable_keep": {
        "mean": 0.019604,
        "std": 0.010949355414817804
      },
      "ambiguous_keep": {
        "mean": 0.048999999999999995,
        "std": 0.027387909741343898
      },
      "unknown_keep": {
        "mean": 0.013063999999999997,
        "std": 0.00730976771176759
      },
      "bucket_score_gate_mean": {
        "mean": 0.5815556037425995,
        "std": 0.06241620881157872
      },
      "unknown_score_gate_mean": {
        "mean": 0.40952964425086974,
        "std": 0.08526177378060049
      }
    },
    "ThreeBucketV5EMAProto": {
      "reliable_size": {
        "mean": 196.04,
        "std": 109.49355414817805
      },
      "ambiguous_size": {
        "mean": 490.0,
        "std": 273.87909741343896
      },
      "unknown_size": {
        "mean": 130.64,
        "std": 73.09767711767591
      },
      "reliable_keep": {
        "mean": 0.019604,
        "std": 0.010949355414817804
      },
      "ambiguous_keep": {
        "mean": 0.048999999999999995,
        "std": 0.027387909741343898
      },
      "unknown_keep": {
        "mean": 0.013063999999999997,
        "std": 0.00730976771176759
      },
      "bucket_score_gate_mean": {
        "mean": 0.5815556037425995,
        "std": 0.06241620881157872
      },
      "unknown_score_gate_mean": {
        "mean": 0.40952964425086974,
        "std": 0.08526177378060049
      }
    },
    "ThreeBucketV6Curriculum": {
      "reliable_size": {
        "mean": 359.36,
        "std": 200.87366776160582
      },
      "ambiguous_size": {
        "mean": 490.0,
        "std": 273.87909741343896
      },
      "weak_size": {
        "mean": 653.48,
        "std": 365.3457671850051
      },
      "unknown_size": {
        "mean": 130.64,
        "std": 73.09767711767591
      },
      "reliable_keep": {
        "mean": 0.035936,
        "std": 0.020087366776160583
      },
      "ambiguous_keep": {
        "mean": 0.048999999999999995,
        "std": 0.027387909741343898
      },
      "weak_keep": {
        "mean": 0.065348,
        "std": 0.03653457671850052
      },
      "unknown_keep": {
        "mean": 0.013063999999999997,
        "std": 0.00730976771176759
      },
      "bucket_score_gate_mean": {
        "mean": 0.5717585396766662,
        "std": 0.056647555027759644
      },
      "unknown_score_gate_mean": {
        "mean": 0.4135627031326294,
        "std": 0.08651878604922564
      }
    },
    "ThreeBucketV7Promotion": {
      "reliable_size": {
        "mean": 261.24,
        "std": 146.03267579552187
      },
      "ambiguous_size": {
        "mean": 457.32,
        "std": 255.71949006675263
      },
      "weak_size": {
        "mean": 816.96,
        "std": 456.5778338903456
      },
      "unknown_size": {
        "mean": 97.96,
        "std": 54.866004046221555
      },
      "reliable_keep": {
        "mean": 0.1599420600787331,
        "std": 0.0002401081496911431
      },
      "ambiguous_keep": {
        "mean": 0.27994275839297234,
        "std": 0.0002754536494897166
      },
      "weak_keep": {
        "mean": 0.5001715186596343,
        "std": 0.00030394303101683313
      },
      "unknown_keep": {
        "mean": 0.059943662868660326,
        "std": 0.00023299647667889963
      },
      "bucket_score_gate_mean": {
        "mean": 0.5777678883075714,
        "std": 0.057635833860590645
      },
      "promoted_reliable": {
        "mean": 229.36,
        "std": 128.22819658717813
      },
      "promoted_ambiguous": {
        "mean": 261.92,
        "std": 148.0637484328963
      },
      "stage2_reliable_size": {
        "mean": 490.6,
        "std": 274.26046014691946
      },
      "stage2_ambiguous_size": {
        "mean": 491.48,
        "std": 274.80671316399827
      },
      "stage2_weak_size": {
        "mean": 488.16,
        "std": 272.6999347267982
      },
      "stage2_unknown_size": {
        "mean": 163.24,
        "std": 91.42922071198026
      },
      "promote_score_gate_mean": {
        "mean": 0.6521600699424743,
        "std": 0.12816073105678588
      },
      "unknown_score_gate_mean": {
        "mean": 0.41192142367362977,
        "std": 0.08948055127879014
      }
    },
    "ThreeBucketV8Adaptive": {
      "reliable_size": {
        "mean": 197.8,
        "std": 109.52625256074454
      },
      "ambiguous_size": {
        "mean": 328.2,
        "std": 182.68508422966556
      },
      "weak_size": {
        "mean": 565.32,
        "std": 321.09583865257423
      },
      "unknown_size": {
        "mean": 98.44,
        "std": 54.73213315777122
      },
      "reliable_keep": {
        "mean": 0.01978,
        "std": 0.010952625256074454
      },
      "ambiguous_keep": {
        "mean": 0.03282,
        "std": 0.018268508422966553
      },
      "weak_keep": {
        "mean": 0.056532,
        "std": 0.032109583865257425
      },
      "unknown_keep": {
        "mean": 0.009844,
        "std": 0.0054732133157771225
      },
      "bucket_score_gate_mean": {
        "mean": 0.5518129587173461,
        "std": 0.058721933729685316
      },
      "promoted_reliable": {
        "mean": 105.12,
        "std": 83.11645805735469
      },
      "promoted_ambiguous": {
        "mean": 297.24,
        "std": 269.3536381785106
      },
      "stage2_reliable_size": {
        "mean": 197.8,
        "std": 109.52625256074454
      },
      "stage2_ambiguous_size": {
        "mean": 328.2,
        "std": 182.68508422966556
      },
      "stage2_weak_size": {
        "mean": 565.32,
        "std": 321.09583865257423
      },
      "stage2_unknown_size": {
        "mean": 98.44,
        "std": 54.73213315777122
      },
      "promote_score_gate_mean": {
        "mean": 0.5957566452026367,
        "std": 0.05801527821778758
      },
      "stability_gate_mean": {
        "mean": 0.6298345875740051,
        "std": 0.05904941573361726
      },
      "refresh_rounds": {
        "mean": 3.0,
        "std": 0.0
      },
      "unknown_score_gate_mean": {
        "mean": 0.4074494457244873,
        "std": 0.03462806406788335
      }
    }
  }
}